drw4e/__init__.py
drw4e-0.0.33.dist-info/LICENSE
drw4e-0.0.33.dist-info/METADATA
drw4e-0.0.33.dist-info/WHEEL
drw4e-0.0.33.dist-info/top_level.txt
drw4e-0.0.33.dist-info/RECORD
