Metadata-Version: 2.1
Name: drw4e
Version: 0.0.33
Summary: A Python package to fit a damped random walk model on astronomical brightness time series data with four different types of measurement error.
Home-page: https://github.com/HW0327/drw4e
Author: Haoyu Wang
Author-email: haoyuwoody0327@gmail.com
Classifier: Programming Language :: Python :: 3
Classifier: License :: OSI Approved :: MIT License
Classifier: Operating System :: OS Independent
Requires-Python: >=3.6
License-File: LICENSE
Requires-Dist: numpy
Requires-Dist: scipy
Requires-Dist: pandas
